QProgEdit/__init__.py
QProgEdit/_qcolorscheme.py
QProgEdit/_qeditor.py
QProgEdit/_qeditorcfg.py
QProgEdit/_qeditorconst.py
QProgEdit/_qeditorfind.py
QProgEdit/_qeditorprefs.py
QProgEdit/_qeditorshortcut.py
QProgEdit/_qeditorstatus.py
QProgEdit/_qlangmenu.py
QProgEdit/_qlexer.py
QProgEdit/_qlineeditfind.py
QProgEdit/_qprogedit.py
QProgEdit/_qsymboltreewidgetitem.py
QProgEdit/_qtabcornerwidget.py
QProgEdit/_qtabmanager.py
QProgEdit/_quiloader.py
QProgEdit/py3compat.py
QProgEdit/pyqt5compat.py
QProgEdit/clean/__init__.py
QProgEdit/clean/_python.py
QProgEdit/symbols/__init__.py
QProgEdit/symbols/_python.py
QProgEdit/ui/findWidget.ui
QProgEdit/ui/prefsWidget.ui
QProgEdit/validate/__init__.py
QProgEdit/validate/_python.py
python_qprogedit-4.1.2.dist-info/DESCRIPTION.rst
python_qprogedit-4.1.2.dist-info/METADATA
python_qprogedit-4.1.2.dist-info/RECORD
python_qprogedit-4.1.2.dist-info/WHEEL
python_qprogedit-4.1.2.dist-info/metadata.json
python_qprogedit-4.1.2.dist-info/top_level.txt
