Metadata-Version: 2.0
Name: python-qprogedit
Version: 4.1.2
Summary: A QScintilla-based text-editor component
Home-page: https://github.com/smathot/QProgEdit
Author: Sebastiaan Mathot
Author-email: s.mathot@cogsci.nl
License: GNU GPL Version 3
Platform: UNKNOWN
Classifier: Development Status :: 4 - Beta
Classifier: Intended Audience :: End Users/Desktop
Classifier: Topic :: Text Editors
Classifier: Environment :: MacOS X
Classifier: Environment :: Win32 (MS Windows)
Classifier: Environment :: X11 Applications
Classifier: License :: OSI Approved :: GNU General Public License v3 or later (GPLv3+)
Classifier: Programming Language :: Python :: 2
Classifier: Programming Language :: Python :: 3
Requires-Dist: qtpy
